.gitattributes
.gitignore
.pre-commit-config.yaml
CONTRIBUTING.md
LICENSE
MANIFEST.in
README.md
environment.yml
pyproject.toml
pytest.ini
readthedocs.yml
setup.cfg
setup.py
starry_process.gif
.github/workflows/examples.yml
.github/workflows/joss.yml
.github/workflows/tests.yml
.github/workflows/wheels.yml
docs/Makefile
docs/api.rst
docs/conf.py
docs/examples.rst
docs/generate_readme_plots.py
docs/hacks.py
docs/index.rst
docs/install.rst
docs/samples_0.png
docs/samples_1.png
docs/samples_2.png
docs/samples_3.png
docs/_static/custom.css
docs/notebooks/Ensemble.ipynb
docs/notebooks/Latitude.ipynb
docs/notebooks/Prior.ipynb
docs/notebooks/Quickstart.ipynb
docs/notebooks/TimeVariability.ipynb
docs/notebooks/TimeVariabilityInference.ipynb
docs/notebooks/notebook_config.py
docs/sphinx_rtd_theme/LICENSE
docs/sphinx_rtd_theme/__init__.py
docs/sphinx_rtd_theme/breadcrumbs.html
docs/sphinx_rtd_theme/footer.html
docs/sphinx_rtd_theme/layout.html
docs/sphinx_rtd_theme/search.html
docs/sphinx_rtd_theme/searchbox.html
docs/sphinx_rtd_theme/theme.conf
docs/sphinx_rtd_theme/versions.html
docs/sphinx_rtd_theme/locale/en/LC_MESSAGES/sphinx.po
docs/sphinx_rtd_theme/locale/es/LC_MESSAGES/sphinx.po
docs/sphinx_rtd_theme/locale/nl/LC_MESSAGES/sphinx.po
docs/sphinx_rtd_theme/locale/ru/LC_MESSAGES/sphinx.po
docs/sphinx_rtd_theme/static/css/badge_only.css
docs/sphinx_rtd_theme/static/css/theme.css
docs/sphinx_rtd_theme/static/fonts/FontAwesome.otf
docs/sphinx_rtd_theme/static/fonts/Roboto-Slab-Bold.woff
docs/sphinx_rtd_theme/static/fonts/Roboto-Slab-Bold.woff2
docs/sphinx_rtd_theme/static/fonts/Roboto-Slab-Light.woff
docs/sphinx_rtd_theme/static/fonts/Roboto-Slab-Light.woff2
docs/sphinx_rtd_theme/static/fonts/Roboto-Slab-Regular.woff
docs/sphinx_rtd_theme/static/fonts/Roboto-Slab-Regular.woff2
docs/sphinx_rtd_theme/static/fonts/Roboto-Slab-Thin.woff
docs/sphinx_rtd_theme/static/fonts/Roboto-Slab-Thin.woff2
docs/sphinx_rtd_theme/static/fonts/fontawesome-webfont.eot
starry_process.egg-info/PKG-INFO
starry_process.egg-info/SOURCES.txt
starry_process.egg-info/dependency_links.txt
starry_process.egg-info/entry_points.txt
starry_process.egg-info/not-zip-safe
starry_process.egg-info/requires.txt
starry_process.egg-info/top_level.txt
