Metadata-Version: 2.1
Name: starry-process
Version: 0.9.8
Summary: interpretable gaussian processes for stellar light curves
Home-page: https://github.com/rodluger/starry_process
Author: Rodrigo Luger
Author-email: rodluger@gmail.com
License: MIT
Platform: UNKNOWN
Provides-Extra: app
Provides-Extra: tests
Provides-Extra: docs
